[
  {
    "constant": true,
    "inputs": [],
    "name": "governor",
    "outputs": [
      {
        "name": "",
        "type": "address"
      }
    ],
    "payable": false,
    "stateMutability": "view",
    "type": "function"
  },
  {
    "constant": true,
    "inputs": [
      {
        "name": "",
        "type": "bytes32"
      }
    ],
    "name": "domains",
    "outputs": [
      {
        "name": "owner",
        "type": "address"
      },
      {
        "name": "subgraphID",
        "type": "bytes32"
      }
    ],
    "payable": false,
    "stateMutability": "view",
    "type": "function"
  },
  {
    "constant": false,
    "inputs": [
      {
        "name": "_newGovernor",
        "type": "address"
      }
    ],
    "name": "transferGovernance",
    "outputs": [
      {
        "name": "",
        "type": "bool"
      }
    ],
    "payable": false,
    "stateMutability": "nonpayable",
    "type": "function"
  },
  {
    "inputs": [
      {
        "name": "_governor",
        "type": "address"
      }
    ],
    "payable": false,
    "stateMutability": "nonpayable",
    "type": "constructor"
  },
  {
    "anonymous": false,
    "inputs": [
      {
        "indexed": true,
        "name": "topLevelDomainHash",
        "type": "bytes32"
      },
      {
        "indexed": true,
        "name": "owner",
        "type": "address"
      },
      {
        "indexed": false,
        "name": "domainName",
        "type": "string"
      }
    ],
    "name": "DomainAdded",
    "type": "event"
  },
  {
    "anonymous": false,
    "inputs": [
      {
        "indexed": true,
        "name": "domainHash",
        "type": "bytes32"
      },
      {
        "indexed": true,
        "name": "newOwner",
        "type": "address"
      }
    ],
    "name": "DomainTransferred",
    "type": "event"
  },
  {
    "anonymous": false,
    "inputs": [
      {
        "indexed": true,
        "name": "topLevelDomainHash",
        "type": "bytes32"
      },
      {
        "indexed": true,
        "name": "registeredHash",
        "type": "bytes32"
      },
      {
        "indexed": false,
        "name": "subdomainName",
        "type": "string"
      },
      {
        "indexed": true,
        "name": "owner",
        "type": "address"
      }
    ],
    "name": "SubgraphCreated",
    "type": "event"
  },
  {
    "anonymous": false,
    "inputs": [
      {
        "indexed": true,
        "name": "domainHash",
        "type": "bytes32"
      },
      {
        "indexed": true,
        "name": "subgraphID",
        "type": "bytes32"
      }
    ],
    "name": "SubgraphIDUpdated",
    "type": "event"
  },
  {
    "anonymous": false,
    "inputs": [
      {
        "indexed": true,
        "name": "domainHash",
        "type": "bytes32"
      }
    ],
    "name": "DomainDeleted",
    "type": "event"
  },
  {
    "anonymous": false,
    "inputs": [
      {
        "indexed": true,
        "name": "account",
        "type": "address"
      },
      {
        "indexed": true,
        "name": "ipfsHash",
        "type": "bytes32"
      }
    ],
    "name": "AccountMetadataChanged",
    "type": "event"
  },
  {
    "anonymous": false,
    "inputs": [
      {
        "indexed": true,
        "name": "domainHash",
        "type": "bytes32"
      },
      {
        "indexed": true,
        "name": "ipfsHash",
        "type": "bytes32"
      }
    ],
    "name": "SubgraphMetadataChanged",
    "type": "event"
  },
  {
    "anonymous": false,
    "inputs": [
      {
        "indexed": true,
        "name": "_from",
        "type": "address"
      },
      {
        "indexed": true,
        "name": "_to",
        "type": "address"
      }
    ],
    "name": "GovernanceTransferred",
    "type": "event"
  },
  {
    "constant": false,
    "inputs": [
      {
        "name": "_domainName",
        "type": "string"
      }
    ],
    "name": "registerDomain",
    "outputs": [],
    "payable": false,
    "stateMutability": "nonpayable",
    "type": "function"
  },
  {
    "constant": false,
    "inputs": [
      {
        "name": "_topLevelDomainHash",
        "type": "bytes32"
      },
      {
        "name": "_subdomainName",
        "type": "string"
      },
      {
        "name": "_ipfsHash",
        "type": "bytes32"
      }
    ],
    "name": "createSubgraph",
    "outputs": [],
    "payable": false,
    "stateMutability": "nonpayable",
    "type": "function"
  },
  {
    "constant": false,
    "inputs": [
      {
        "name": "_domainHash",
        "type": "bytes32"
      },
      {
        "name": "_subgraphID",
        "type": "bytes32"
      }
    ],
    "name": "updateDomainSubgraphID",
    "outputs": [],
    "payable": false,
    "stateMutability": "nonpayable",
    "type": "function"
  },
  {
    "constant": false,
    "inputs": [
      {
        "name": "_domainHash",
        "type": "bytes32"
      }
    ],
    "name": "deleteSubdomain",
    "outputs": [],
    "payable": false,
    "stateMutability": "nonpayable",
    "type": "function"
  },
  {
    "constant": false,
    "inputs": [
      {
        "name": "_domainHash",
        "type": "bytes32"
      },
      {
        "name": "_newOwner",
        "type": "address"
      }
    ],
    "name": "transferDomainOwnership",
    "outputs": [],
    "payable": false,
    "stateMutability": "nonpayable",
    "type": "function"
  },
  {
    "constant": false,
    "inputs": [
      {
        "name": "_ipfsHash",
        "type": "bytes32"
      }
    ],
    "name": "changeAccountMetadata",
    "outputs": [],
    "payable": false,
    "stateMutability": "nonpayable",
    "type": "function"
  },
  {
    "constant": false,
    "inputs": [
      {
        "name": "_domainHash",
        "type": "bytes32"
      },
      {
        "name": "_ipfsHash",
        "type": "bytes32"
      }
    ],
    "name": "changeSubgraphMetadata",
    "outputs": [],
    "payable": false,
    "stateMutability": "nonpayable",
    "type": "function"
  }
]
